{
    "dimension": 8,
    "numbers": [
        {
            "value": 0,
            "x": 1,
            "y": 1
        },
        {
            "value": 0,
            "x": 0,
            "y": 3
        },
        {
            "value": 0,
            "x": 0,
            "y": 7
        },
        {
            "value": 0,
            "x": 1,
            "y": 5
        },
        {
            "value": 0,
            "x": 2,
            "y": 2
        },
        {
            "value": 0,
            "x": 2,
            "y": 6
        },
        {
            "value": 0,
            "x": 3,
            "y": 0
        },
        {
            "value": 0,
            "x": 4,
            "y": 3
        },
        {
            "value": 2,
            "x": 4,
            "y": 6
        },
        {
            "value": 0,
            "x": 5,
            "y": 1
        },
        {
            "value": 1,
            "x": 6,
            "y": 5
        },
        {
            "value": 0,
            "x": 7,
            "y": 0
        },
        {
            "value": 0,
            "x": 7,
            "y": 3
        }
    ]
}